README.md
setup.cfg
setup.py
ANBOT/__init__.py
ANBOT/__main__.py
ANBOT/cli.py
ANBOT/events.py
ANBOT/global_checks.py
ANBOT/json_io.py
ANBOT/setup.py
ANBOT.egg-info/PKG-INFO
ANBOT.egg-info/SOURCES.txt
ANBOT.egg-info/dependency_links.txt
ANBOT.egg-info/entry_points.txt
ANBOT.egg-info/requires.txt
ANBOT.egg-info/top_level.txt
ANBOT/commands/__init__.py
ANBOT/commands/commands.py
ANBOT/commands/context.py
ANBOT/commands/converter.py
ANBOT/commands/errors.py
ANBOT/commands/requires.py
ANBOT/downloader/__init__.py
ANBOT/downloader/checks.py
ANBOT/downloader/converters.py
ANBOT/downloader/downloader.py
ANBOT/downloader/errors.py
ANBOT/downloader/installable.py
ANBOT/downloader/json_mixins.py
ANBOT/downloader/log.py
ANBOT/downloader/repo_manager.py
ANBOT/feature/__init__.py
ANBOT/feature/developer/__init__.py
ANBOT/feature/developer/developer.py
ANBOT/main/__init__.py
ANBOT/main/bot.py
ANBOT/main/checks.py
ANBOT/main/config.py
ANBOT/main/data.py
ANBOT/main/errors.py
ANBOT/main/helps.py
ANBOT/main/manage.py
ANBOT/main/rpc.py
ANBOT/main/sentry.py
ANBOT/utils/__init__.py
ANBOT/utils/antispam.py
ANBOT/utils/caching.py
ANBOT/utils/chat_formatting.py
ANBOT/utils/common_filters.py
ANBOT/utils/data_converter.py
ANBOT/utils/embed.py
ANBOT/utils/menus.py
ANBOT/utils/mod.py
ANBOT/utils/predicates.py
ANBOT/utils/tunnel.py