Metadata-Version: 2.1
Name: ANBOT
Version: 3.1.0
Summary: A highly customisable Discord bot
Home-page: https://github.com/aditya-nugraha-bot
Author: aditya-nugraha-bot
Author-email: adityanugraha5405@gmail.com
License: GPL-3.0
Keywords: ANBOT-DISCORD
Platform: UNKNOWN
Classifier: Development Status :: 5 - Production/Stable
Classifier: Framework :: AsyncIO
Classifier: Framework :: Pytest
Classifier: Intended Audience :: Developers
Classifier: Intended Audience :: End Users/Desktop
Classifier: License :: OSI Approved :: GNU General Public License v3 (GPLv3)
Classifier: Natural Language :: English
Classifier: Operating System :: OS Independent
Classifier: Programming Language :: Python :: 3.7
Classifier: Topic :: Communications :: Chat
Classifier: Topic :: Documentation :: Sphinx
Requires-Python: >=3.7
